<news>
<date>25 juin 2011</date>
<title>Sortie de Wine 1.3.23</title>
<body>
<p> La version de développement 1.3.23 de Wine est disponible.</p>
<p> <a href="{$root}/announce/1.3.23">Nouveautés</a> de cette version :
<ul>
  <li>Prise en charge des proxies COM sans stub sous x86-64.</li>
  <li>Le dxdiag intégré donne à présent des informations authentiques.</li>
  <li>Format de bitmap monochrome dans le moteur DIB.</li>
  <li>Ébauche d'un véritable shell Explorer intégré.</li>
  <li>Plusieurs nouvelles fonctions D3DX9.</li>
  <li>Prise en charge améliorée du façonnage de texte brahmique.</li>
  <li>Diverses corrections de bogues.</li>
</ul></p>
<p><p>Le <a
href="http://prdownloads.sourceforge.net/wine/wine-1.3.23.tar.bz2">code
source</a> est disponible dès à présent.
Les paquets binaires sont en cours de construction, et apparaîtront sous peu
sur leurs <a href="{$root}/download">sites de téléchargement</a> respectifs.
</p></body></news>
