<news>
<date>16 mars 2012</date>
<title>Sortie de Wine 1.5.0</title>
<body>
<p> La version de développement 1.5.0 de Wine est disponible.</p>
<p> <a href="{$root}/announce/1.5.0">Nouveautés</a> de cette version :
<ul>
  <li>Nouvelle version du moteur Gecko.</li>
  <li>Prise en charge partielle de la Corbeille sous Mac OS X.</li>
  <li>Prise en charge des dégradés de chemins dans GdiPlus.</li>
  <li>Diverses améliorations MSXML.</li>
  <li>Correctifs dans le traitement des exceptions 64 bits.</li>
  <li>Diverses corrections de bogues.</li>
</ul></p>
<p><p>Le <a
href="http://prdownloads.sourceforge.net/wine/wine-1.5.0.tar.bz2">code
source</a> est disponible dès à présent.
Les paquets binaires sont en cours de construction, et apparaîtront sous peu
sur leurs <a href="{$root}/download">sites de téléchargement</a> respectifs.
</p></body></news>
