<news>
<date>4. Februar 2011</date>
<title>Wine 1.3.13 freigegeben</title>
<body>
<p> Die Entwicklungsversion 1.3.13 von Wine ist jetzt verfügbar.</p>
<p> <a href="{$root}/announce/1.3.13">Neuerungen (en)</a> in dieser Version:
<ul>
  <li>Werkzeuge zum erzeugen von MSI-Installer.</li>
  <li>Verbesserungen an der Zwischenablage.</li>
  <li>Unterstützung für po-Dateien im Message-Compiler.</li>
  <li>Verbesserungen am Wine Debugger.</li>
  <li>Verschiedene Fehlerbehebungen.</li>
</ul></p>
<p><p>Der Quellcode ist jetzt <a href="http://prdownloads.sourceforge.net/wine/wine-1.3.13.tar.bz2">verfügbar</a>.
Binär-Downloads werden gerade erstellt und stehen bald auf den jeweiligen <a href="{$root}/download">Download-Seiten</a> zur Verfügung.
</p></body></news>
