<news>
<date>21. Juni 2013</date>
<title>Wine 1.6-rc3 freigegeben</title>
<body>
<p> Die Entwicklungsversion 1.6-rc3 von Wine ist jetzt verf체gbar.</p>
<p> <a href="{$root}/announce/1.6-rc3">Neuerungen (en)</a> in dieser Version:</p>
<ul>
  <li>Nur Fehlerbehebungen, da wir uns im Code-Freeze befinden.</li>
</ul>
<p>Der Quellcode ist jetzt <a href="http://prdownloads.sourceforge.net/wine/wine-1.6-rc3.tar.bz2">verf체gbar</a>.
Bin채rpakete werden gerade erstellt und stehen bald auf den jeweiligen <a href="{$root}/download">Download-Seiten</a> zur Verf체gung.
</p></body></news>
